randomml/__init__.py
randomml/base.py
randomml/classifier.py
randomml/ensemble.py
randomml/ffnn.py
randomml/mlp_utils.py
randomml/mlpedrvfl.py
randomml/regressor.py
random_ml-0.1.0.dist-info/METADATA
random_ml-0.1.0.dist-info/WHEEL
random_ml-0.1.0.dist-info/top_level.txt
random_ml-0.1.0.dist-info/RECORD
