Metadata-Version: 2.2
Name: random-ml
Version: 0.1.0
Summary: An implementation of Rabdomization based ML algorithm.
Home-page: https://github.com/yuvrajiro/random-ml
Author: Your Name
Author-email: Rahul Goswami <rahul.goswami@iitg.ac.in>
Requires-Python: >=3.7
Requires-Dist: numpy
Requires-Dist: torch
Requires-Dist: scikit-learn
Dynamic: author
Dynamic: home-page
Dynamic: requires-python
